mystic/__info__.py
mystic/__init__.py
mystic/__main__.py
mystic/_counter.py
mystic/_genSow.py
mystic/_scipy060optimize.py
mystic/_scipyoptimize.py
mystic/_signal.py
mystic/_symbolic.py
mystic/abstract_ensemble_solver.py
mystic/abstract_launcher.py
mystic/abstract_map_solver.py
mystic/abstract_sampler.py
mystic/abstract_solver.py
mystic/bounds.py
mystic/collapse.py
mystic/constraints.py
mystic/coupler.py
mystic/differential_evolution.py
mystic/ensemble.py
mystic/filters.py
mystic/forward_model.py
mystic/helputil.py
mystic/linesearch.py
mystic/mask.py
mystic/metropolis.py
mystic/monitors.py
mystic/munge.py
mystic/penalty.py
mystic/pools.py
mystic/python_map.py
mystic/samplers.py
mystic/scemtools.py
mystic/scipy_optimize.py
mystic/scripts.py
mystic/search.py
mystic/solvers.py
mystic/strategy.py
mystic/support.py
mystic/svc.py
mystic/svr.py
mystic/symbolic.py
mystic/termination.py
mystic/tools.py
mystic/cache/__init__.py
mystic/cache/archive.py
mystic/cache/function.py
mystic/math/__init__.py
mystic/math/_rbf.py
mystic/math/approx.py
mystic/math/compressed.py
mystic/math/discrete.py
mystic/math/distance.py
mystic/math/grid.py
mystic/math/integrate.py
mystic/math/interpolate.py
mystic/math/legacydata.py
mystic/math/measures.py
mystic/math/poly.py
mystic/math/samples.py
mystic/math/stats.py
mystic/models/__init__.py
mystic/models/__main__.py
mystic/models/_model_helper.py
mystic/models/abstract_model.py
mystic/models/br8.py
mystic/models/circle.py
mystic/models/dejong.py
mystic/models/functions.py
mystic/models/lorentzian.py
mystic/models/mogi.py
mystic/models/nag.py
mystic/models/pohlheim.py
mystic/models/poly.py
mystic/models/schittkowski.py
mystic/models/storn.py
mystic/models/venkataraman.py
mystic/models/wavy.py
mystic/models/wolfram.py
mystic/tests/__init__.py
mystic/tests/__main__.py
mystic/tests/_log.py
mystic/tests/check_SOW.py
mystic/tests/test_1d2d_expect.py
mystic/tests/test_boundsconstrained.py
mystic/tests/test_cache.py
mystic/tests/test_collapse.py
mystic-0.4.5.dist-info/LICENSE
mystic-0.4.5.dist-info/METADATA
mystic-0.4.5.dist-info/WHEEL
mystic-0.4.5.dist-info/top_level.txt
mystic-0.4.5.dist-info/RECORD
