Metadata-Version: 2.1
Name: mystic
Version: 0.4.5
Summary: constrained nonlinear optimization for scientific machine learning, UQ, and AI
Home-page: https://github.com/uqfoundation/mystic
Download-URL: https://pypi.org/project/mystic/#files
Author: Mike McKerns
Author-email: mmckerns@uqfoundation.org
Maintainer: Mike McKerns
Maintainer-email: mmckerns@uqfoundation.org
License: BSD-3-Clause
Project-URL: Documentation, http://mystic.rtfd.io
Project-URL: Source Code, https://github.com/uqfoundation/mystic
Project-URL: Bug Tracker, https://github.com/uqfoundation/mystic/issues
Platform: Linux
Platform: Windows
Platform: Mac
Classifier: Development Status :: 5 - Production/Stable
Classifier: Intended Audience :: Developers
Classifier: Intended Audience :: Science/Research
Classifier: License :: OSI Approved :: BSD License
Classifier: Programming Language :: Python :: 3
Classifier: Programming Language :: Python :: 3.9
Classifier: Programming Language :: Python :: 3.10
Classifier: Programming Language :: Python :: 3.11
Classifier: Programming Language :: Python :: 3.12
Classifier: Programming Language :: Python :: 3.13
Classifier: Programming Language :: Python :: 3.14
Classifier: Programming Language :: Python :: Implementation :: CPython
Classifier: Programming Language :: Python :: Implementation :: PyPy
Classifier: Topic :: Scientific/Engineering
Classifier: Topic :: Software Development
Requires-Python: >=3.9
License-File: LICENSE
Requires-Dist: dill>=0.4.1
Requires-Dist: klepto>=0.2.8
Requires-Dist: numpy>=1.0
Requires-Dist: sympy>=0.6.7
Requires-Dist: mpmath>=0.19
Provides-Extra: math
Requires-Dist: scipy>=0.6.0; extra == "math"
Provides-Extra: parallel
Requires-Dist: pathos>=0.3.5; extra == "parallel"
Requires-Dist: pyina>=0.3.1; extra == "parallel"
Provides-Extra: plotting
Requires-Dist: matplotlib>=0.91; extra == "plotting"
